brainseg/__init__.py
brainseg/__main__.py
brainseg/brainsegnifti.py
brainseg/brainsegnifti_helper.py
brainseg/brainsegpicture.py
brainseg-0.0.5.dist-info/LICENSE
brainseg-0.0.5.dist-info/METADATA
brainseg-0.0.5.dist-info/WHEEL
brainseg-0.0.5.dist-info/entry_points.txt
brainseg-0.0.5.dist-info/top_level.txt
brainseg-0.0.5.dist-info/RECORD
