Metadata-Version: 2.1
Name: brainseg
Version: 0.0.5
Summary: A brain segmentation tool
Home-page: https://github.com/alleetw101/brainseg
Author: Alan Lee
Author-email: alleetw101@gmail.com
License: UNKNOWN
Platform: UNKNOWN
Classifier: Programming Language :: Python :: 3
Classifier: License :: OSI Approved :: MIT License
Classifier: Operating System :: OS Independent
Requires-Python: >=3.8
Requires-Dist: Tensorflow (>=2.0)
Requires-Dist: Pillow (>=8.0)
Requires-Dist: niftiprocessing
